llm_tokenizers/__init__.py
llm_tokenizers/abstract_tokenizer.py
llm_tokenizers/deepseek_tokenizer.py
llm_tokenizers/main_tokenizer.py
llm_tokenizers/resources/__init__.py
llm_tokenizers/resources/deepseek_tokenizer/__init__.py
llm_tokenizers/resources/deepseek_tokenizer/tokenizer.json
llm_tokenizers/resources/deepseek_tokenizer/tokenizer_config.json
llm_tokenizers-0.1.4.dist-info/LICENSE
llm_tokenizers-0.1.4.dist-info/METADATA
llm_tokenizers-0.1.4.dist-info/WHEEL
llm_tokenizers-0.1.4.dist-info/entry_points.txt
llm_tokenizers-0.1.4.dist-info/top_level.txt
llm_tokenizers-0.1.4.dist-info/RECORD
