Metadata-Version: 2.1
Name: llm_tokenizers
Version: 0.1.4
Summary: LLM tokenizers tools
Author-email: Fang JiaWei <fjw12998@hotmail.com>
Project-URL: Homepage, https://gitee.com/sky_flash/llm_tokenizers
Project-URL: Documentation, https://gitee.com/sky_flash/llm_tokenizers/docs
Classifier: Programming Language :: Python :: 3
Classifier: Programming Language :: Python :: 3.8
Classifier: Programming Language :: Python :: 3.9
Classifier: Programming Language :: Python :: 3.10
Classifier: Programming Language :: Python :: 3.11
Classifier: Programming Language :: Python :: 3.12
Classifier: License :: OSI Approved :: GNU General Public License v3 (GPLv3)
Classifier: Operating System :: OS Independent
Requires-Python: >=3.8
License-File: LICENSE
Requires-Dist: requests<3.0.0,>=2.32.4
Requires-Dist: transformers<5.0.0,>=4.46.3
